adbc_driver_postgresql/libadbc_driver_postgresql.so
adbc_driver_postgresql/_version.py
adbc_driver_postgresql/dbapi.py
adbc_driver_postgresql/__init__.py
adbc_driver_postgresql/_static_version.py
adbc_driver_postgresql-1.10.0.dist-info/RECORD
adbc_driver_postgresql-1.10.0.dist-info/WHEEL
adbc_driver_postgresql-1.10.0.dist-info/top_level.txt
adbc_driver_postgresql-1.10.0.dist-info/METADATA
adbc_driver_postgresql-1.10.0.dist-info/licenses/NOTICE.txt
adbc_driver_postgresql-1.10.0.dist-info/licenses/LICENSE.txt
