Metadata-Version: 2.4
Name: adbc-driver-postgresql
Version: 1.10.0
Summary: A libpq-based ADBC driver for working with PostgreSQL.
Author-email: Apache Arrow Developers <dev@arrow.apache.org>
License-Expression: Apache-2.0
Project-URL: homepage, https://arrow.apache.org/adbc/
Project-URL: repository, https://github.com/apache/arrow-adbc
Requires-Python: >=3.10
License-File: LICENSE.txt
License-File: NOTICE.txt
Requires-Dist: adbc-driver-manager
Requires-Dist: importlib-resources>=1.3
Provides-Extra: dbapi
Requires-Dist: pandas; extra == "dbapi"
Requires-Dist: pyarrow>=14.0.1; extra == "dbapi"
Provides-Extra: test
Requires-Dist: pandas; extra == "test"
Requires-Dist: polars; extra == "test"
Requires-Dist: pyarrow>=14.0.1; extra == "test"
Requires-Dist: pytest; extra == "test"
Dynamic: license-file
